full_adder.v
//-----------------------------------------------------
// Module: full_adder
// Description: A simple Full Adder using dataflow modeling.
// Inputs: a, b, cin
// Outputs: sum, cout
//-----------------------------------------------------
module full_adder (
    input  wire a,    // Input A
    input  wire b,    // Input B
    input  wire cin,  // Carry In
    output wire sum,  // Sum output
    output wire cout  // Carry Out
);

    // Calculate Sum using XOR
    assign sum = a ^ b ^ cin;

    // Calculate Carry Out using AND/OR logic
    assign cout = (a & b) | (a & cin) | (b & cin);
    // Alternative calculation: assign cout = (a & b) | (cin & (a ^ b));

endmodule

full_adder_tb.v
//-----------------------------------------------------
// Module: full_adder_tb
// Description: Testbench for the full_adder module.
//              Cycles through all 8 input combinations.
//-----------------------------------------------------
`timescale 1ns / 1ps // Timescale for simulation delays

module full_adder_tb;

    // Testbench signals (inputs to DUT)
    reg a,b,cin;

    // Testbench signals (outputs from DUT)
    wire sum,cout;

    // Instantiate the Device Under Test (DUT) - the full_adder
    // Make sure the module name 'full_adder' matches the one in full_adder.v
    full_adder dut (
        .a(a),        // Connect testbench 'a' to DUT's 'a' input
        .b(b),        // Connect testbench 'b' to DUT's 'b' input
        .cin(cin),    // Connect testbench 'cin' to DUT's 'cin' input
        .sum(sum),    // Connect DUT's 'sum' output to testbench 'sum'
        .cout(cout)   // Connect DUT's 'cout' output to testbench 'cout'
    );

    // Test sequence generation
    initial begin
        // Optional: Setup waveform dumping for GTKWave
        $dumpfile("full_adder.vcd"); // Specify the VCD file name
        $dumpvars(0, full_adder_tb); // Dump all variables in this module scope

        $display("Starting Full Adder Testbench...");
        $display("Time (ns) | a | b | cin || sum | cout |");
        $display("----------|---|---|-----||-----|------|");

        // Initialize inputs
        a = 1'b0; // 1'b0 means 1-bit binary value 0
        b = 1'b0;
        cin = 1'b0;
        #10; // Wait 10 nanoseconds

        // Loop through all 8 possible input combinations
        for (integer i = 0; i < 8; i = i + 1) begin
            {a, b, cin} = i; // Assign the 3 bits of 'i' directly to a, b, cin
            #10; // Wait 10 ns for outputs to settle after input change
            $display("    %0t    | %b | %b |  %b  ||  %b  |  %b   |",
                     $time, a, b, cin, sum, cout); // Use $time for current sim time
        end

        #20; // Wait a bit longer at the end
        $display("Testbench finished.");
        $finish; // End the simulation
    end

endmodule

full_adder.vcd
$date
	Sun Apr 27 18:43:25 2025
$end
$version
	Icarus Verilog
$end
$timescale
	1ps
$end
$scope module full_adder_tb $end
$var wire 1 ! sum $end
$var wire 1 " cout $end
$var reg 1 # a $end
$var reg 1 $ b $end
$var reg 1 % cin $end
$scope module dut $end
$var wire 1 # a $end
$var wire 1 $ b $end
$var wire 1 % cin $end
$var wire 1 " cout $end
$var wire 1 ! sum $end
$upscope $end
$scope begin $ivl_for_loop0 $end
$var integer 32 & i [31:0] $end
$upscope $end
$upscope $end
$enddefinitions $end
$comment Show the parameter values. $end
$dumpall
$end
#0
$dumpvars
bx &
0%
0$
0#
0"
0!
$end
#10000
b0 &
#20000
1!
1%
b1 &
#30000
1!
1$
0%
b10 &
#40000
1"
0!
1%
b11 &
#50000
0"
1!
1#
0$
0%
b100 &
#60000
1"
0!
1%
b101 &
#70000
0!
1$
0%
b110 &
#80000
1!
1%
b111 &
#90000
b1000 &
